commandeft-0.6.1.dist-info/METADATA
commandeft-0.6.1.dist-info/WHEEL
commandeft-0.6.1.dist-info/entry_points.txt
commandeft-0.6.1.dist-info/licenses/LICENSE
commandeft/.coverage
commandeft/.pytest_cache/.gitignore
commandeft/.pytest_cache/CACHEDIR.TAG
commandeft/.pytest_cache/README.md
commandeft/.pytest_cache/v/cache/nodeids
commandeft/.pytest_cache/v/cache/stepwise
commandeft/__init__.py
commandeft/constants/__init__.py
commandeft/constants/consts.py
commandeft/core/__init__.py
commandeft/core/cli.py
commandeft/core/decision.py
commandeft/core/generation.py
commandeft/core/history_cache.py
commandeft/main.py
commandeft/util/__init__.py
commandeft/util/config_util.py
commandeft/util/gen_util.py
commandeft/util/interactive_util.py
commandeft/util/versioning_util.py
commandeft-0.6.1.dist-info/RECORD
