Metadata-Version: 2.1
Name: commandeft
Version: 0.6.1
Summary: CommanDeft is a CLI tool that converts natural language prompts into executable commands or scripts using OpenAI's chat models.
Keywords: commandeft cli tool shell commands prompt-based command generation natural language prompts shell commands shell scripts shell command generation intelligent code generation language-to-code conversion developer-friendly simplified scripting code efficiency streamline workflow intelligent suggestions efficient command composition gpt-3.5-turbo gpt-4 shell command suggestion interactive mode guided prompt command execution
Author-Email: Petros Sidirokastritis <sidirope@gmail.com>
License: MIT
Project-URL: Homepage, https://github.com/Ferrum-Citadel/commandeft
Requires-Python: <=3.11.6,>=3.8.1
Requires-Dist: PyJWT==2.7.0
Requires-Dist: Pygments==2.15.1
Requires-Dist: aiohttp==3.8.4
Requires-Dist: aiosignal==1.3.1
Requires-Dist: async-timeout==4.0.2
Requires-Dist: attrs==23.1.0
Requires-Dist: cachetools==5.3.1
Requires-Dist: certifi>=2023.7.22
Requires-Dist: cffi==1.15.1
Requires-Dist: charset-normalizer<4.0,>=2.0
Requires-Dist: click==8.1.3
Requires-Dist: cryptography>=41.0.5
Requires-Dist: frozenlist==1.3.3
Requires-Dist: idna==3.4
Requires-Dist: multidict<7.0,>=4.5
Requires-Dist: openai==0.28.1
Requires-Dist: pip-licenses==4.3.2
Requires-Dist: prettytable==3.7.0
Requires-Dist: prompt-toolkit<4.0.0,>=3.0.1
Requires-Dist: pycparser==2.21
Requires-Dist: pyperclip==1.8.2
Requires-Dist: regex==2023.6.3
Requires-Dist: six==1.16.0
Requires-Dist: tqdm==4.65.0
Requires-Dist: urllib3==2.0.2
Requires-Dist: wcwidth==0.2.6
Requires-Dist: yarl<2.0,>=1.0
Requires-Dist: InquirerPy>=0.3.4
Requires-Dist: tiktoken>=0.4.0
Requires-Dist: packaging>=23.1
Requires-Dist: pytest; extra == "dev"
Requires-Dist: pytest-cov; extra == "dev"
Requires-Dist: pytest-pep8; extra == "dev"
Requires-Dist: pytest-mock>=3.12.0; extra == "dev"
Provides-Extra: dev
